{
  "formatVersion": 1,
  "nodes": [
    {
      "id": "3",
      "name": "Princess",
      "children": [],
      "components": [
        {
          "type": "SpriteRenderer",
          "config": {
            "spriteAssetId": "43",
            "animationId": "4",
            "horizontalFlip": true,
            "verticalFlip": false,
            "castShadow": false,
            "receiveShadow": false,
            "color": "ffffff",
            "overrideOpacity": false,
            "opacity": null,
            "materialType": "basic",
            "shaderAssetId": null
          },
          "id": "0"
        },
        {
          "type": "Behavior",
          "config": {
            "behaviorName": "PrincessBehavior",
            "propertyValues": {}
          },
          "id": "1"
        },
        {
          "type": "ArcadeBody2D",
          "config": {
            "type": "box",
            "movable": true,
            "width": 5,
            "height": 7.8,
            "offset": {
              "x": 0,
              "y": 0
            },
            "tileMapAssetId": null,
            "tileSetPropertyName": null,
            "layersIndex": null
          },
          "id": "2"
        }
      ],
      "position": {
        "x": 136,
        "y": 141,
        "z": 0
      },
      "orientation": {
        "x": 0,
        "y": 0,
        "z": 0,
        "w": 1
      },
      "scale": {
        "x": 1,
        "y": 1,
        "z": 1
      },
      "visible": true,
      "layer": 0,
      "prefab": null
    },
    {
      "id": "4",
      "name": "Camera",
      "children": [],
      "components": [
        {
          "type": "Behavior",
          "config": {
            "behaviorName": "CameraBehavior",
            "propertyValues": {}
          },
          "id": "0"
        }
      ],
      "position": {
        "x": 3.2339420318603516,
        "y": -2.5186924934387207,
        "z": 0
      },
      "orientation": {
        "x": 0,
        "y": 0,
        "z": 0,
        "w": 1
      },
      "scale": {
        "x": 1,
        "y": 1,
        "z": 1
      },
      "visible": true,
      "layer": 0,
      "prefab": null
    },
    {
      "id": "7",
      "name": "Map",
      "children": [
        {
          "id": "1",
          "name": "Map",
          "children": [],
          "components": [
            {
              "type": "TileMapRenderer",
              "config": {
                "tileMapAssetId": "25",
                "tileSetAssetId": null,
                "castShadow": false,
                "receiveShadow": false,
                "materialType": "basic",
                "shaderAssetId": null
              },
              "id": "0"
            },
            {
              "type": "ArcadeBody2D",
              "config": {
                "type": "tileMap",
                "movable": true,
                "width": 1,
                "height": 1,
                "offset": {
                  "x": 0,
                  "y": 0
                },
                "tileMapAssetId": "25",
                "tileSetPropertyName": null,
                "layersIndex": "0"
              },
              "id": "1"
            }
          ],
          "position": {
            "x": 0,
            "y": 0,
            "z": 0
          },
          "orientation": {
            "x": 0,
            "y": 0,
            "z": 0,
            "w": 1
          },
          "scale": {
            "x": 1,
            "y": 1,
            "z": 1
          },
          "visible": true,
          "layer": 0,
          "prefab": null
        }
      ],
      "components": [],
      "position": {
        "x": 112.65005493164062,
        "y": 82.26351928710938,
        "z": 0
      },
      "orientation": {
        "x": 0,
        "y": 0,
        "z": 0,
        "w": 1
      },
      "scale": {
        "x": 1,
        "y": 1,
        "z": 1
      },
      "visible": true,
      "layer": 0,
      "prefab": null
    },
    {
      "id": "14",
      "name": "Map_Green",
      "children": [
        {
          "id": "16",
          "name": "Map_Green",
          "children": [],
          "components": [
            {
              "type": "TileMapRenderer",
              "config": {
                "tileMapAssetId": "63",
                "tileSetAssetId": null,
                "castShadow": false,
                "receiveShadow": false,
                "materialType": "basic",
                "shaderAssetId": null
              },
              "id": "0"
            },
            {
              "type": "ArcadeBody2D",
              "config": {
                "type": "tileMap",
                "movable": true,
                "width": 1,
                "height": 1,
                "offset": {
                  "x": 0,
                  "y": 0
                },
                "tileMapAssetId": "63",
                "tileSetPropertyName": null,
                "layersIndex": "0"
              },
              "id": "1"
            },
            {
              "type": "Behavior",
              "config": {
                "behaviorName": "MapGreenBehavior",
                "propertyValues": {}
              },
              "id": "2"
            }
          ],
          "position": {
            "x": -77.56134033203125,
            "y": -48.21429443359375,
            "z": 0
          },
          "orientation": {
            "x": 0,
            "y": 0,
            "z": 0,
            "w": 1
          },
          "scale": {
            "x": 1,
            "y": 1,
            "z": 1
          },
          "visible": true,
          "layer": 0,
          "prefab": null
        }
      ],
      "components": [],
      "position": {
        "x": 190.21139526367188,
        "y": 130.47781372070312,
        "z": 0
      },
      "orientation": {
        "x": 0,
        "y": 0,
        "z": 0,
        "w": 1
      },
      "scale": {
        "x": 1,
        "y": 1,
        "z": 1
      },
      "visible": true,
      "layer": 0,
      "prefab": null
    },
    {
      "id": "15",
      "name": "Map_Orange",
      "children": [
        {
          "id": "17",
          "name": "Map_Orange",
          "children": [],
          "components": [
            {
              "type": "TileMapRenderer",
              "config": {
                "tileMapAssetId": "64",
                "tileSetAssetId": null,
                "castShadow": false,
                "receiveShadow": false,
                "materialType": "basic",
                "shaderAssetId": null
              },
              "id": "0"
            },
            {
              "type": "ArcadeBody2D",
              "config": {
                "type": "tileMap",
                "movable": true,
                "width": 1,
                "height": 1,
                "offset": {
                  "x": 0,
                  "y": 0
                },
                "tileMapAssetId": "64",
                "tileSetPropertyName": null,
                "layersIndex": "0"
              },
              "id": "1"
            },
            {
              "type": "Behavior",
              "config": {
                "behaviorName": "MapOrangeBehavior",
                "propertyValues": {}
              },
              "id": "2"
            }
          ],
          "position": {
            "x": -77.56134033203125,
            "y": -48.21429443359375,
            "z": 0
          },
          "orientation": {
            "x": 0,
            "y": 0,
            "z": 0,
            "w": 1
          },
          "scale": {
            "x": 1,
            "y": 1,
            "z": 1
          },
          "visible": true,
          "layer": 0,
          "prefab": null
        }
      ],
      "components": [],
      "position": {
        "x": 190.21139526367188,
        "y": 130.47781372070312,
        "z": 0
      },
      "orientation": {
        "x": 0,
        "y": 0,
        "z": 0,
        "w": 1
      },
      "scale": {
        "x": 1,
        "y": 1,
        "z": 1
      },
      "visible": true,
      "layer": 0,
      "prefab": null
    },
    {
      "id": "9",
      "name": "Platforms",
      "children": [
        {
          "id": "11",
          "name": "MovingPlatform",
          "children": [],
          "components": [],
          "position": {
            "x": 46.14593505859375,
            "y": 54.162384033203125,
            "z": 0
          },
          "orientation": {
            "x": 0,
            "y": 0,
            "z": 0,
            "w": 1
          },
          "scale": {
            "x": 1,
            "y": 1,
            "z": 1
          },
          "visible": true,
          "layer": 0,
          "prefab": {
            "sceneAssetId": "60"
          }
        },
        {
          "id": "12",
          "name": "Prefab",
          "children": [],
          "components": [],
          "position": {
            "x": 76.61933898925781,
            "y": 54.0894775390625,
            "z": 0
          },
          "orientation": {
            "x": 0,
            "y": 0,
            "z": 0,
            "w": 1
          },
          "scale": {
            "x": 1,
            "y": 1,
            "z": 1
          },
          "visible": true,
          "layer": 0,
          "prefab": {
            "sceneAssetId": "61"
          }
        }
      ],
      "components": [],
      "position": {
        "x": 112.65005493164062,
        "y": 82.26351928710938,
        "z": 0
      },
      "orientation": {
        "x": 0,
        "y": 0,
        "z": 0,
        "w": 1
      },
      "scale": {
        "x": 1,
        "y": 1,
        "z": 1
      },
      "visible": true,
      "layer": 0,
      "prefab": null
    },
    {
      "id": "13",
      "name": "Switch",
      "children": [
        {
          "id": "18",
          "name": "Prefab",
          "children": [],
          "components": [],
          "position": {
            "x": 134.3393406867981,
            "y": 134.08424305915833,
            "z": 0
          },
          "orientation": {
            "x": 0,
            "y": 0,
            "z": 0,
            "w": 1
          },
          "scale": {
            "x": 1,
            "y": 1,
            "z": 1
          },
          "visible": true,
          "layer": 0,
          "prefab": {
            "sceneAssetId": "66"
          }
        }
      ],
      "components": [],
      "position": {
        "x": -6.412415027618408,
        "y": 3.0226447582244873,
        "z": 0
      },
      "orientation": {
        "x": 0,
        "y": 0,
        "z": 0,
        "w": 1
      },
      "scale": {
        "x": 1,
        "y": 1,
        "z": 1
      },
      "visible": true,
      "layer": 0,
      "prefab": null
    }
  ]
}